odoo8_addon_geoengine_geoname_geocoder-8.0.0.1.0.99.dev23-py2.7-nspkg.pth
odoo8_addon_geoengine_geoname_geocoder-8.0.0.1.0.99.dev23.dist-info/DESCRIPTION.rst
odoo8_addon_geoengine_geoname_geocoder-8.0.0.1.0.99.dev23.dist-info/METADATA
odoo8_addon_geoengine_geoname_geocoder-8.0.0.1.0.99.dev23.dist-info/RECORD
odoo8_addon_geoengine_geoname_geocoder-8.0.0.1.0.99.dev23.dist-info/WHEEL
odoo8_addon_geoengine_geoname_geocoder-8.0.0.1.0.99.dev23.dist-info/metadata.json
odoo8_addon_geoengine_geoname_geocoder-8.0.0.1.0.99.dev23.dist-info/namespace_packages.txt
odoo8_addon_geoengine_geoname_geocoder-8.0.0.1.0.99.dev23.dist-info/top_level.txt
odoo_addons/geoengine_geoname_geocoder/README.rst
odoo_addons/geoengine_geoname_geocoder/__init__.py
odoo_addons/geoengine_geoname_geocoder/__openerp__.py
odoo_addons/geoengine_geoname_geocoder/company_view.xml
odoo_addons/geoengine_geoname_geocoder/res_company.py
odoo_addons/geoengine_geoname_geocoder/res_partner.py
odoo_addons/geoengine_geoname_geocoder/i18n/am.po
odoo_addons/geoengine_geoname_geocoder/i18n/ar.po
odoo_addons/geoengine_geoname_geocoder/i18n/bg.po
odoo_addons/geoengine_geoname_geocoder/i18n/bs.po
odoo_addons/geoengine_geoname_geocoder/i18n/ca.po
odoo_addons/geoengine_geoname_geocoder/i18n/ca_ES.po
odoo_addons/geoengine_geoname_geocoder/i18n/cs.po
odoo_addons/geoengine_geoname_geocoder/i18n/da.po
odoo_addons/geoengine_geoname_geocoder/i18n/de.po
odoo_addons/geoengine_geoname_geocoder/i18n/el_GR.po
odoo_addons/geoengine_geoname_geocoder/i18n/en_AU.po
odoo_addons/geoengine_geoname_geocoder/i18n/en_GB.po
odoo_addons/geoengine_geoname_geocoder/i18n/es.po
odoo_addons/geoengine_geoname_geocoder/i18n/es_AR.po
odoo_addons/geoengine_geoname_geocoder/i18n/es_CL.po
odoo_addons/geoengine_geoname_geocoder/i18n/es_CO.po
odoo_addons/geoengine_geoname_geocoder/i18n/es_CR.po
odoo_addons/geoengine_geoname_geocoder/i18n/es_DO.po
odoo_addons/geoengine_geoname_geocoder/i18n/es_EC.po
odoo_addons/geoengine_geoname_geocoder/i18n/es_ES.po
odoo_addons/geoengine_geoname_geocoder/i18n/es_MX.po
odoo_addons/geoengine_geoname_geocoder/i18n/es_PE.po
odoo_addons/geoengine_geoname_geocoder/i18n/es_PY.po
odoo_addons/geoengine_geoname_geocoder/i18n/es_VE.po
odoo_addons/geoengine_geoname_geocoder/i18n/et.po
odoo_addons/geoengine_geoname_geocoder/i18n/eu.po
odoo_addons/geoengine_geoname_geocoder/i18n/fa.po
odoo_addons/geoengine_geoname_geocoder/i18n/fi.po
odoo_addons/geoengine_geoname_geocoder/i18n/fr.po
odoo_addons/geoengine_geoname_geocoder/i18n/fr_CA.po
